InnovationLabHunt/__init__.py
InnovationLabHunt/hunt.py
InnovationLabHunt-1.1.dist-info/METADATA
InnovationLabHunt-1.1.dist-info/WHEEL
InnovationLabHunt-1.1.dist-info/top_level.txt
InnovationLabHunt-1.1.dist-info/RECORD
