Metadata-Version: 2.1
Name: InnovationLabHunt
Version: 1.1
Summary: Hunt package
Author: PES Innovation Lab
Author-email: innovationlab@pes.edu
